gfg/__init__.py
gfg/gfg.py
deep_clone_gfg_test-1.0.0.dist-info/METADATA
deep_clone_gfg_test-1.0.0.dist-info/WHEEL
deep_clone_gfg_test-1.0.0.dist-info/entry_points.txt
deep_clone_gfg_test-1.0.0.dist-info/top_level.txt
deep_clone_gfg_test-1.0.0.dist-info/RECORD
