Metadata-Version: 2.1
Name: deep-clone-gfg-test
Version: 1.0.0
Summary: Demo Package for GfG Article.
Home-page: https://github.com/rajan-personal/deep-clone-gfg-test
Author: rajan gupta
Author-email: 96rajangupta@gmail.com
License: MIT
Keywords: geeksforgeeks gfg article python package
Platform: UNKNOWN
Classifier: Programming Language :: Python :: 3
Classifier: License :: OSI Approved :: MIT License
Classifier: Operating System :: OS Independent
